verbatim_core/__init__.py
verbatim_core/cli.py
verbatim_core/enhance.py
verbatim_core/extractors.py
verbatim_core/llm_client.py
verbatim_core/models.py
verbatim_core/providers.py
verbatim_core/response_builder.py
verbatim_core/transform.py
verbatim_core/types.py
verbatim_core/universal_document.py
verbatim_core/extractor_models/dataset.py
verbatim_core/extractor_models/model.py
verbatim_core/extractor_models/preprocess_ragbench.py
verbatim_core/extractor_models/train.py
verbatim_core/extractor_models/trainer.py
verbatim_core/templates/__init__.py
verbatim_core/templates/base.py
verbatim_core/templates/contextual.py
verbatim_core/templates/filler.py
verbatim_core/templates/manager.py
verbatim_core/templates/question_specific.py
verbatim_core/templates/random.py
verbatim_core/templates/static.py
verbatim_core/templates/structured.py
verbatim_rag/__init__.py
verbatim_rag/chunker_providers.py
verbatim_rag/chunking.py
verbatim_rag/cli.py
verbatim_rag/core.py
verbatim_rag/document.py
verbatim_rag/embedding_providers.py
verbatim_rag/extractors.py
verbatim_rag/index.py
verbatim_rag/intent.py
verbatim_rag/llm_client.py
verbatim_rag/models.py
verbatim_rag/providers.py
verbatim_rag/rerankers.py
verbatim_rag/response_builder.py
verbatim_rag/schema.py
verbatim_rag/streaming.py
verbatim_rag/transform.py
verbatim_rag/universal_document.py
verbatim_rag/verbatim_doc.py
verbatim_rag/ingestion/__init__.py
verbatim_rag/ingestion/document_processor.py
verbatim_rag/ingestion/hierarchical_chunker.py
verbatim_rag/ingestion/schema_adapter.py
verbatim_rag/templates/__init__.py
verbatim_rag/tools/upload_to_hub.py
verbatim_rag/vector_stores/__init__.py
verbatim_rag/vector_stores/base.py
verbatim_rag/vector_stores/hybrid_search.py
verbatim_rag/vector_stores/milvus_base.py
verbatim_rag/vector_stores/milvus_cloud.py
verbatim_rag/vector_stores/milvus_local.py
verbatim_rag/vector_stores/utils.py
verbatim_rag-0.1.9.dist-info/METADATA
verbatim_rag-0.1.9.dist-info/WHEEL
verbatim_rag-0.1.9.dist-info/entry_points.txt
verbatim_rag-0.1.9.dist-info/licenses/LICENSE
verbatim_rag-0.1.9.dist-info/RECORD
