Metadata-Version: 2.4
Name: verbatim-rag
Version: 0.1.9
Summary: A minimalistic RAG system that prevents hallucination by ensuring all generated content is explicitly derived from source documents
Project-URL: Homepage, https://github.com/krlabsorg/verbatim-rag
Project-URL: Bug Tracker, https://github.com/krlabsorg/verbatim-rag/issues
Author-email: Adam Kovacs <kovacs@krlabs.eu>
License: MIT
License-File: LICENSE
Classifier: License :: OSI Approved :: MIT License
Classifier: Operating System :: OS Independent
Classifier: Programming Language :: Python :: 3
Requires-Python: >=3.10
Requires-Dist: chonkie
Requires-Dist: datasets==3.4.1
Requires-Dist: docling
Requires-Dist: fastapi>=0.100.0
Requires-Dist: huggingface-hub>=0.16.0
Requires-Dist: numpy>=1.24.3
Requires-Dist: openai>=1.3.0
Requires-Dist: pandas>=2.0.3
Requires-Dist: pydantic-settings>=2.0.0
Requires-Dist: pydantic>=2.0.0
Requires-Dist: pymilvus>=2.6.3
Requires-Dist: pymilvus[milvus-lite]
Requires-Dist: pyyaml>=6.0
Requires-Dist: scikit-learn==1.6.1
Requires-Dist: sentence-transformers>=5.0.0
Requires-Dist: tiktoken>=0.5.1
Requires-Dist: torch>=2.6.0
Requires-Dist: tqdm>=4.65.0
Requires-Dist: transformers==4.53.3
Requires-Dist: uvicorn>=0.20.0
